__init__.py
sparkpolars/__init__.py
sparkpolars/_from_polars_to_spark.py
sparkpolars/_from_spark_to_polars.py
sparkpolars/_importlib_utils.py
sparkpolars/_version.py
sparkpolars/config.py
sparkpolars/sparkpolars.py
sparkpolars/polyspark/__init__.py
sparkpolars/polyspark/sql/__init__.py
sparkpolars/polyspark/sql/dataframe.py
sparkpolars/polyspark/sql/functions.py
sparkpolars/polyspark/sql/types.py
sparkpolars/polyspark/sql/window.py
sparkpolars-0.1.1rc18.dist-info/licenses/LICENSE
sparkpolars-0.1.1rc18.dist-info/METADATA
sparkpolars-0.1.1rc18.dist-info/WHEEL
sparkpolars-0.1.1rc18.dist-info/top_level.txt
sparkpolars-0.1.1rc18.dist-info/RECORD
